donv/USAGE.md
donv/__init__.py
donv/attach.py
donv/base.py
donv/build.py
donv/donv.py
donv/option.py
donv/remove.py
donv/remove_image.py
donv/restart.py
donv/restart_attach.py
donv/run.py
donv/stop.py
donv/version.py
donv/__pycache__/__init__.cpython-38.pyc
donv/__pycache__/version.cpython-38.pyc
donv/docker/Dockerfile
donv/docker/dockerfile.sh
donv/docker/requirements.txt
donv-0.1.22.dist-info/LICENSE
donv-0.1.22.dist-info/METADATA
donv-0.1.22.dist-info/WHEEL
donv-0.1.22.dist-info/entry_points.txt
donv-0.1.22.dist-info/top_level.txt
donv-0.1.22.dist-info/RECORD
