Metadata-Version: 2.1
Name: donv
Version: 0.1.22
Summary: Easy setup for docker env.
Home-page: https://github.com/nemodleo/donv
Author: Hyun Park
Author-email: nemod.leo@snu.ac.kr
License: MIT
Keywords: docker build dockerfile run env images ps
Classifier: License :: OSI Approved :: MIT License
License-File: LICENSE
